bkdetect-0.1.1.dist-info/licenses/LICENSE
stemmers/__init__.py
stemmers/porter_ru.py
bkdetect-0.1.1.dist-info/METADATA
bkdetect-0.1.1.dist-info/WHEEL
bkdetect-0.1.1.dist-info/entry_points.txt
bkdetect-0.1.1.dist-info/top_level.txt
bkdetect-0.1.1.dist-info/RECORD
