Metadata-Version: 2.4
Name: bkdetect
Version: 0.1.1
Summary: Library for document similarity search
Author-email: Batyr Kotiev <your@email.com>
License: MIT
Classifier: Development Status :: 3 - Alpha
Classifier: Intended Audience :: Developers
Classifier: Topic :: Software Development :: Libraries
Classifier: Programming Language :: Python :: 3
Classifier: Programming Language :: Python :: 3.7
Classifier: Programming Language :: Python :: 3.8
Classifier: Programming Language :: Python :: 3.9
Classifier: Operating System :: OS Independent
Requires-Python: >=3.7
License-File: LICENSE
Requires-Dist: nltk
Requires-Dist: scikit-learn
Requires-Dist: beautifulsoup4
Requires-Dist: pdfminer.six
Requires-Dist: python-docx
Requires-Dist: pdfplumber
Requires-Dist: numpy
Requires-Dist: scipy
Dynamic: license-file
